episodic/__about__.py
episodic/__init__.py
episodic/__main__.py
episodic/snk.yaml
episodic/cli/__init__.py
episodic/workflow/Snakefile
episodic/workflow/__init__.py
episodic/workflow/utils.py
episodic/workflow/envs/arviz.yml
episodic/workflow/envs/beast.yml
episodic/workflow/envs/ggtree.yml
episodic/workflow/envs/phylo.yml
episodic/workflow/envs/plot_traces.yml
episodic/workflow/envs/python.yml
episodic/workflow/profiles/slurm/config.yaml
episodic/workflow/rules/beast.smk
episodic/workflow/rules/config.smk
episodic/workflow/rules/report.smk
episodic/workflow/rules/tree.smk
episodic/workflow/scripts/__init__.py
episodic/workflow/scripts/arviz_output.py
episodic/workflow/scripts/calculate_odds.py
episodic/workflow/scripts/densitree.R
episodic/workflow/scripts/extract_mle.py
episodic/workflow/scripts/phylo_rate_quantile_analysis.py
episodic/workflow/scripts/plot_mcc_tree.R
episodic/workflow/scripts/plot_traces.py
episodic/workflow/scripts/populate_beast_template.py
episodic/workflow/scripts/tree_converter.py
episodic/workflow/templates/beast_xml_template.jinja
episodic-0.6.1.dist-info/METADATA
episodic-0.6.1.dist-info/WHEEL
episodic-0.6.1.dist-info/entry_points.txt
episodic-0.6.1.dist-info/licenses/LICENSE.txt
episodic-0.6.1.dist-info/RECORD
