Metadata-Version: 2.3
Name: episodic
Version: 0.6.1
Summary: A complete pipeline for fitting and testing Fixed Local Clock (FLC) molecular clock models for episodic evolution.
Project-URL: Documentation, https://github.com/wytamma/episodic#readme
Project-URL: Issues, https://github.com/wytamma/episodic/issues
Project-URL: Source, https://github.com/wytamma/episodic
Author-email: Wytamma Wirth <wytamma.wirth@me.com>
License-Expression: MIT
License-File: LICENSE.txt
Classifier: Development Status :: 4 - Beta
Classifier: Programming Language :: Python
Classifier: Programming Language :: Python :: 3.9
Classifier: Programming Language :: Python :: 3.10
Classifier: Programming Language :: Python :: 3.11
Classifier: Programming Language :: Python :: Implementation :: CPython
Classifier: Programming Language :: Python :: Implementation :: PyPy
Requires-Python: <3.12,>=3.9
Requires-Dist: snk-cli==0.3.1
